armilla.py
armilla-0.0.7.dist-info/METADATA
armilla-0.0.7.dist-info/WHEEL
armilla-0.0.7.dist-info/top_level.txt
armilla-0.0.7.dist-info/RECORD
